{
  "dramhit_2023": [
    {
      "rsize": 187904768,
      "htsize": 268435456,
      "mops": 713.8
    },
    {
      "rsize": 93952384,
      "htsize": 134217728,
      "mops": 613.4
    },
    {
      "rsize": 46976128,
      "htsize": 67108864,
      "mops": 387.4
    },
    {
      "rsize": 23488000,
      "htsize": 33554432,
      "mops": 276.9
    },
    {
      "rsize": 11744000,
      "htsize": 16777216,
      "mops": 114.9
    },
    {
      "rsize": 5872000,
      "htsize": 8388608,
      "mops": 100.6
    },
    {
      "rsize": 2935936,
      "htsize": 4194304,
      "mops": 57.0
    },
    {
      "rsize": 1467904,
      "htsize": 2097152,
      "mops": 27.8
    },
    {
      "rsize": 733952,
      "htsize": 1048576,
      "mops": 14.2
    },
    {
      "rsize": 366976,
      "htsize": 524288,
      "mops": 8.2
    }
  ],
  "dramhit_2025": [
    {
      "rsize": 187904768,
      "htsize": 268435456,
      "mops": 953.4
    },
    {
      "rsize": 93952384,
      "htsize": 134217728,
      "mops": 1138.8
    },
    {
      "rsize": 46976128,
      "htsize": 67108864,
      "mops": 568.4
    },
    {
      "rsize": 23488000,
      "htsize": 33554432,
      "mops": 472.5
    },
    {
      "rsize": 11744000,
      "htsize": 16777216,
      "mops": 193.5
    },
    {
      "rsize": 5872000,
      "htsize": 8388608,
      "mops": 137.4
    },
    {
      "rsize": 2935936,
      "htsize": 4194304,
      "mops": 70.6
    },
    {
      "rsize": 1467904,
      "htsize": 2097152,
      "mops": 36.7
    },
    {
      "rsize": 733952,
      "htsize": 1048576,
      "mops": 18.6
    },
    {
      "rsize": 366976,
      "htsize": 524288,
      "mops": 11.5
    }
  ],
  "GROWT": [
    {
      "rsize": 187904768,
      "htsize": 268435456,
      "mops": 129.6
    },
    {
      "rsize": 93952384,
      "htsize": 134217728,
      "mops": 408.2
    },
    {
      "rsize": 46976128,
      "htsize": 67108864,
      "mops": 405.2
    },
    {
      "rsize": 23488000,
      "htsize": 33554432,
      "mops": 244.6
    },
    {
      "rsize": 11744000,
      "htsize": 16777216,
      "mops": 165.0
    },
    {
      "rsize": 5872000,
      "htsize": 8388608,
      "mops": 108.4
    },
    {
      "rsize": 2935936,
      "htsize": 4194304,
      "mops": 99.6
    },
    {
      "rsize": 1467904,
      "htsize": 2097152,
      "mops": 46.1
    },
    {
      "rsize": 733952,
      "htsize": 1048576,
      "mops": 30.5
    },
    {
      "rsize": 366976,
      "htsize": 524288,
      "mops": 15.7
    }
  ],
  "CLHT": [
    {
      "rsize": 187904768,
      "htsize": 268435456,
      "mops": 116.3
    },
    {
      "rsize": 93952384,
      "htsize": 134217728,
      "mops": 430.8
    },
    {
      "rsize": 46976128,
      "htsize": 67108864,
      "mops": 306.8
    },
    {
      "rsize": 23488000,
      "htsize": 33554432,
      "mops": 198.5
    },
    {
      "rsize": 11744000,
      "htsize": 16777216,
      "mops": 125.7
    },
    {
      "rsize": 5872000,
      "htsize": 8388608,
      "mops": 79.4
    },
    {
      "rsize": 2935936,
      "htsize": 4194304,
      "mops": 52.7
    },
    {
      "rsize": 1467904,
      "htsize": 2097152,
      "mops": 32.2
    },
    {
      "rsize": 733952,
      "htsize": 1048576,
      "mops": 16.6
    },
    {
      "rsize": 366976,
      "htsize": 524288,
      "mops": 8.4
    }
  ]
}